{
  "global": {
    "weakest": {
      "value": "0.1",
      "type": "opacity"
    },
    "color": {
      "light": {
        "background": {
          "base": {
            "value": "#fff",
            "type": "color",
            "description": "The default light background color, used e.g. as a backdrop for charts or cards."
          },
          "stronger": {
            "value": "{color.light.petrol50}",
            "type": "color",
            "description": "A slightly shaded background color, used e.g. as a backdrop behind card elements."
          },
          "strongest": {
            "value": "{color.light.petrol100}",
            "type": "color",
            "description": "A shaded background color, used e.g. as a backdrop in containers."
          }
        },
        "foreground": {
          "base": {
            "value": "{color.light.petrol600}",
            "type": "color",
            "description": "Used for elements in the foreground that have a strong contrast to the background."
          },
          "weaker": {
            "value": "{color.light.petrol200}",
            "type": "color",
            "description": "Used for elements in the foreground that have a weaker contrast to the background (e.g. axes)."
          },
          "weakest": {
            "value": "{color.light.petrol100}",
            "type": "color"
          }
        },
        "text": {
          "base": {
            "value": "{color.light.petrol800}",
            "type": "color",
            "description": "Default text color for strong background contrast."
          },
          "weaker": {
            "value": "{color.light.petrol500}",
            "type": "color",
            "description": "Text color with weaker background contrast."
          },
          "weakest": {
            "value": "{color.light.petrol200}",
            "type": "color"
          }
        },
        "brand": {
          "base": {
            "value": "{color.light.petrol500}",
            "type": "color",
            "description": "Main theme color, usually the brand color."
          },
          "stronger": {
            "value": "{color.light.petrol600}",
            "type": "color",
            "description": "Stronger version of theme color"
          },
          "weaker": {
            "value": "{color.light.petrol300}",
            "type": "color",
            "description": "Weaker version of theme color"
          }
        },
        "functional": {
          "accent": {
            "value": "#95AD28",
            "type": "color",
            "description": "Used for author-driven accents of parts of charts, texts and other elements."
          },
          "filtered-out": {
            "value": "#e4e1d8",
            "type": "color",
            "description": "Used for visual marks in charts that have been filtered out."
          },
          "not-available": {
            "value": "#b2b2b2",
            "type": "color",
            "description": "Used for visual marks (e.g. countries in maps) where data is missing from the dataset."
          },
          "warn": {
            "value": "#ffe060",
            "type": "color"
          }
        },
        "category": {
          "0": {
            "value": "#5ABAC1",
            "type": "color",
            "description": "Used for nominal data of category 0."
          },
          "1": {
            "value": "#3C96E5",
            "type": "color",
            "description": "Used for nominal data of category 1."
          },
          "2": {
            "value": "#F5C54A",
            "type": "color",
            "description": "Used for nominal data of category 2."
          },
          "3": {
            "value": "#DE54B7",
            "type": "color"
          },
          "4": {
            "value": "#6363c0",
            "type": "color",
            "description": "Used for nominal data of category 4."
          },
          "5": {
            "value": "#1F5F84",
            "type": "color"
          }
        },
        "diverging": {
          "positive-2": {
            "value": "#1c4e94",
            "type": "color",
            "description": "Fifth step in the base diverging color scale, used for the highest (most positive) value. "
          },
          "positive-1": {
            "value": "#6fbedf",
            "type": "color",
            "description": "Fourth step in the base diverging color scale, used for values higher than zero (or data median)."
          },
          "neutral": {
            "value": "#d6dae5",
            "type": "color",
            "description": "Third step in the base diverging color scale, used for zero or data median."
          },
          "negative-1": {
            "value": "#ebc26f",
            "type": "color",
            "description": "Second step in the base diverging color scale, used for values lower than zero (or data median)."
          },
          "negative-2": {
            "value": "#ee8f00",
            "type": "color",
            "description": "First step in the based diverging color scale, used for the lowest (most negative) value. "
          }
        },
        "sequential": {
          "0": {
            "value": "#d7e6f3",
            "type": "color",
            "description": "First step in the base (theme) sequential color scale, used for the lowest value. "
          },
          "1": {
            "value": "#90d3fb",
            "type": "color",
            "description": "Second step in the base (theme) sequential color scale."
          },
          "2": {
            "value": "#008dc8",
            "type": "color",
            "description": "Thirs step in the base (theme) sequential color scale."
          },
          "3": {
            "value": "#0c2d5b",
            "type": "color",
            "description": "Third and final step in the base (theme) sequential color scale."
          }
        },
        "gray100": {
          "value": "#f2f2f2",
          "type": "color",
          "description": "Do not use for UI elements or text. Contrast is 1.11:1 against background #ffffff"
        },
        "gray200": {
          "value": "#d6d7d7",
          "type": "color",
          "description": "Do not use for UI elements or text. Contrast is 1.44:1 against background #ffffff"
        },
        "gray300": {
          "value": "#b2b3b3",
          "type": "color",
          "description": "Do not use for UI elements or text. Contrast is 2.1:1 against background #ffffff"
        },
        "gray400": {
          "value": "#909191",
          "type": "color",
          "description": "Color can be used for UI elements or large text. Contrast is 3.15:1 against background #ffffff"
        },
        "gray500": {
          "value": "#727272",
          "type": "color",
          "description": "Color can be used for small text. Contrast is 4.81:1 against background #ffffff"
        },
        "gray600": {
          "value": "#555555",
          "type": "color",
          "description": "Color can be used for small text. Contrast is 7.46:1 against background #ffffff"
        },
        "gray700": {
          "value": "#393939",
          "type": "color",
          "description": "Color can be used for small text. Contrast is 11.55:1 against background #ffffff"
        },
        "gray800": {
          "value": "#222222",
          "type": "color",
          "description": "Color can be used for small text. Contrast is 15.91:1 against background #ffffff"
        },
        "petrol50": {
          "value": "#F0F3F5",
          "type": "color"
        },
        "petrol100": {
          "value": "#CFD8DE",
          "type": "color",
          "description": "Do not use for UI elements or text. Contrast is 1.45:1 against background #ffffff"
        },
        "petrol200": {
          "value": "#AFBEC7",
          "type": "color",
          "description": "Do not use for UI elements or text. Contrast is 1.9:1 against background #ffffff"
        },
        "petrol300": {
          "value": "#90A5B1",
          "type": "color",
          "description": "Do not use for UI elements or text. Contrast is 2.52:1 against background #ffffff"
        },
        "petrol400": {
          "value": "#798D9B",
          "type": "color",
          "description": "Color can be used for UI elements or large text. Contrast is 3.45:1 against background #ffffff"
        },
        "petrol500": {
          "value": "#59788A",
          "type": "color",
          "description": "Color can be used for small text. Contrast is 4.74:1 against background #ffffff"
        },
        "petrol600": {
          "value": "#214B63",
          "type": "color",
          "description": "Color can be used for small text. Contrast is 6.69:1 against background #ffffff"
        },
        "petrol700": {
          "value": "#193A4D",
          "type": "color",
          "description": "Color can be used for small text. Contrast is 9.44:1 against background #ffffff"
        },
        "petrol800": {
          "value": "#122936",
          "type": "color",
          "description": "Color can be used for small text. Contrast is 13.01:1 against background #ffffff"
        },
        "blue100": {
          "value": "#f1f3f9",
          "type": "color",
          "description": "Do not use for UI elements or text. Contrast is 1.11:1 against background #ffffff"
        },
        "blue200": {
          "value": "#d0d6ed",
          "type": "color",
          "description": "Do not use for UI elements or text. Contrast is 1.44:1 against background #ffffff"
        },
        "blue300": {
          "value": "#a6b2dc",
          "type": "color",
          "description": "Do not use for UI elements or text. Contrast is 2.1:1 against background #ffffff"
        },
        "blue400": {
          "value": "#7e8fc9",
          "type": "color",
          "description": "Color can be used for UI elements or large text. Contrast is 3.15:1 against background #ffffff"
        },
        "blue500": {
          "value": "#5d6fb0",
          "type": "color",
          "description": "Color can be used for small text. Contrast is 4.81:1 against background #ffffff"
        },
        "blue600": {
          "value": "#40518f",
          "type": "color",
          "description": "Color can be used for small text. Contrast is 7.46:1 against background #ffffff"
        },
        "blue700": {
          "value": "#273668",
          "type": "color",
          "description": "Color can be used for small text. Contrast is 11.55:1 against background #ffffff"
        },
        "blue800": {
          "value": "#151f45",
          "type": "color",
          "description": "Color can be used for small text. Contrast is 15.91:1 against background #ffffff"
        },
        "purple100": {
          "value": "#fdf0f8",
          "type": "color",
          "description": "Do not use for UI elements or text. Contrast is 1.11:1 against background #ffffff"
        },
        "purple200": {
          "value": "#f8cae7",
          "type": "color",
          "description": "Do not use for UI elements or text. Contrast is 1.44:1 against background #ffffff"
        },
        "purple300": {
          "value": "#eb99cf",
          "type": "color",
          "description": "Do not use for UI elements or text. Contrast is 2.1:1 against background #ffffff"
        },
        "purple400": {
          "value": "#d36eb5",
          "type": "color",
          "description": "Color can be used for UI elements or large text. Contrast is 3.15:1 against background #ffffff"
        },
        "purple500": {
          "value": "#bb429b",
          "type": "color",
          "description": "Color can be used for small text. Contrast is 4.81:1 against background #ffffff"
        },
        "purple600": {
          "value": "#962576",
          "type": "color",
          "description": "Color can be used for small text. Contrast is 7.46:1 against background #ffffff"
        },
        "purple700": {
          "value": "#6a134d",
          "type": "color",
          "description": "Color can be used for small text. Contrast is 11.55:1 against background #ffffff"
        },
        "purple800": {
          "value": "#410c2f",
          "type": "color",
          "description": "Color can be used for small text. Contrast is 15.91:1 against background #ffffff"
        },
        "red100": {
          "value": "#feeeee",
          "type": "color",
          "description": "Do not use for UI elements or text. Contrast is 1.11:1 against background #ffffff"
        },
        "red200": {
          "value": "#fbcccd",
          "type": "color",
          "description": "Do not use for UI elements or text. Contrast is 1.44:1 against background #ffffff"
        },
        "red300": {
          "value": "#f8999b",
          "type": "color",
          "description": "Do not use for UI elements or text. Contrast is 2.1:1 against background #ffffff"
        },
        "red400": {
          "value": "#eb666d",
          "type": "color",
          "description": "Color can be used for UI elements or large text. Contrast is 3.15:1 against background #ffffff"
        },
        "red500": {
          "value": "#db2735",
          "type": "color",
          "description": "Color can be used for small text. Contrast is 4.81:1 against background #ffffff"
        },
        "red600": {
          "value": "#ab0c19",
          "type": "color",
          "description": "Color can be used for small text. Contrast is 7.46:1 against background #ffffff"
        },
        "red700": {
          "value": "#770811",
          "type": "color",
          "description": "Color can be used for small text. Contrast is 11.55:1 against background #ffffff"
        },
        "red800": {
          "value": "#4a050b",
          "type": "color",
          "description": "Color can be used for small text. Contrast is 15.91:1 against background #ffffff"
        },
        "orange100": {
          "value": "#fff1e2",
          "type": "color",
          "description": "Do not use for UI elements or text. Contrast is 1.11:1 against background #ffffff"
        },
        "orange200": {
          "value": "#ffce99",
          "type": "color",
          "description": "Do not use for UI elements or text. Contrast is 1.44:1 against background #ffffff"
        },
        "orange300": {
          "value": "#fe9c33",
          "type": "color",
          "description": "Do not use for UI elements or text. Contrast is 2.1:1 against background #ffffff"
        },
        "orange400": {
          "value": "#d47b23",
          "type": "color",
          "description": "Color can be used for UI elements or large text. Contrast is 3.15:1 against background #ffffff"
        },
        "orange500": {
          "value": "#a95f1a",
          "type": "color",
          "description": "Color can be used for small text. Contrast is 4.81:1 against background #ffffff"
        },
        "orange600": {
          "value": "#7e4713",
          "type": "color",
          "description": "Color can be used for small text. Contrast is 7.46:1 against background #ffffff"
        },
        "orange700": {
          "value": "#55300d",
          "type": "color",
          "description": "Color can be used for small text. Contrast is 11.55:1 against background #ffffff"
        },
        "orange800": {
          "value": "#331d08",
          "type": "color",
          "description": "Color can be used for small text. Contrast is 15.91:1 against background #ffffff"
        },
        "yellow100": {
          "value": "#fff4c1",
          "type": "color",
          "description": "Do not use for UI elements or text. Contrast is 1.11:1 against background #ffffff"
        },
        "yellow200": {
          "value": "#f8d52d",
          "type": "color",
          "description": "Do not use for UI elements or text. Contrast is 1.44:1 against background #ffffff"
        },
        "yellow300": {
          "value": "#d6af20",
          "type": "color",
          "description": "Do not use for UI elements or text. Contrast is 2.1:1 against background #ffffff"
        },
        "yellow400": {
          "value": "#b58b14",
          "type": "color",
          "description": "Color can be used for UI elements or large text. Contrast is 3.15:1 against background #ffffff"
        },
        "yellow500": {
          "value": "#966a0b",
          "type": "color",
          "description": "Color can be used for small text. Contrast is 4.81:1 against background #ffffff"
        },
        "yellow600": {
          "value": "#704f08",
          "type": "color",
          "description": "Color can be used for small text. Contrast is 7.46:1 against background #ffffff"
        },
        "yellow700": {
          "value": "#4b3505",
          "type": "color",
          "description": "Color can be used for small text. Contrast is 11.55:1 against background #ffffff"
        },
        "yellow800": {
          "value": "#2d2003",
          "type": "color",
          "description": "Color can be used for small text. Contrast is 15.91:1 against background #ffffff"
        },
        "green100": {
          "value": "#dff7f2",
          "type": "color",
          "description": "Do not use for UI elements or text. Contrast is 1.11:1 against background #ffffff"
        },
        "green200": {
          "value": "#96e5d5",
          "type": "color",
          "description": "Do not use for UI elements or text. Contrast is 1.44:1 against background #ffffff"
        },
        "green300": {
          "value": "#53c5ad",
          "type": "color",
          "description": "Do not use for UI elements or text. Contrast is 2.1:1 against background #ffffff"
        },
        "green400": {
          "value": "#20a386",
          "type": "color",
          "description": "Color can be used for UI elements or large text. Contrast is 3.15:1 against background #ffffff"
        },
        "green500": {
          "value": "#19806a",
          "type": "color",
          "description": "Color can be used for small text. Contrast is 4.81:1 against background #ffffff"
        },
        "green600": {
          "value": "#13604f",
          "type": "color",
          "description": "Color can be used for small text. Contrast is 7.46:1 against background #ffffff"
        },
        "green700": {
          "value": "#0d4035",
          "type": "color",
          "description": "Color can be used for small text. Contrast is 11.55:1 against background #ffffff"
        },
        "green800": {
          "value": "#082620",
          "type": "color",
          "description": "Color can be used for small text. Contrast is 15.91:1 against background #ffffff"
        }
      },
      "dark": {
        "background": {
          "base": {
            "value": "#1c1f25",
            "type": "color"
          },
          "weaker": {
            "value": "#4c5873",
            "type": "color",
            "description": "slightly shaded background"
          },
          "weakest": {
            "value": "#636e86",
            "type": "color"
          }
        },
        "foreground": {
          "base": {
            "value": "#eaeaea",
            "type": "color"
          },
          "weaker": {
            "value": "#9597ae",
            "type": "color"
          },
          "weakest": {
            "value": "#696c85",
            "type": "color"
          }
        },
        "text": {
          "weaker": {
            "value": "#a9abbd",
            "type": "color"
          },
          "base": {
            "value": "#eaeaea",
            "type": "color"
          }
        },
        "theme": {
          "base": {
            "value": "#008dc9",
            "type": "color"
          },
          "weaker": {
            "value": "#1f4c7e",
            "type": "color"
          },
          "stronger": {
            "value": "#90d3fb",
            "type": "color"
          }
        },
        "functional": {
          "accent": {
            "value": "#ffcb01",
            "type": "color"
          },
          "not-available": {
            "value": "#cccccc",
            "type": "color"
          },
          "filtered-out": {
            "value": "#474b69",
            "type": "color"
          }
        },
        "category": {
          "0": {
            "value": "#008dc9",
            "type": "color"
          },
          "1": {
            "value": "#f26829",
            "type": "color"
          },
          "2": {
            "value": "#f4a81d",
            "type": "color"
          },
          "3": {
            "value": "#8fba51",
            "type": "color"
          },
          "4": {
            "value": "#8a91f3",
            "type": "color"
          },
          "5": {
            "value": "#bd53bd",
            "type": "color"
          }
        },
        "diverging": {
          "positive-2": {
            "value": "#a1d0ff",
            "type": "color"
          },
          "positive-1": {
            "value": "#6d8ca3",
            "type": "color"
          },
          "neutral": {
            "value": "#3e404f",
            "type": "color"
          },
          "negative-1": {
            "value": "#94815b",
            "type": "color"
          },
          "negative-2": {
            "value": "#f0b847",
            "type": "color"
          }
        },
        "sequential": {
          "0": {
            "value": "#2c3c54",
            "type": "color"
          },
          "1": {
            "value": "#445f7e",
            "type": "color"
          },
          "2": {
            "value": "#72a5c9",
            "type": "color"
          },
          "3": {
            "value": "#90d3fb",
            "type": "color"
          }
        }
      }
    },
    "effect": {
      "depth": {
        "card": {
          "value": {
            "color": "#00000033",
            "type": "dropShadow",
            "x": "0",
            "y": "1",
            "blur": "4",
            "spread": "0"
          },
          "type": "boxShadow"
        },
        "hover": {
          "value": {
            "color": "#00000033",
            "type": "dropShadow",
            "x": "0",
            "y": "5",
            "blur": "6",
            "spread": "0"
          },
          "type": "boxShadow"
        },
        "modal": {
          "value": {
            "color": "#00000033",
            "type": "dropShadow",
            "x": "0",
            "y": "7",
            "blur": "10",
            "spread": "0"
          },
          "type": "boxShadow"
        },
        "ui": {
          "value": {
            "color": "#00000033",
            "type": "dropShadow",
            "x": "0",
            "y": "1",
            "blur": "4",
            "spread": "0"
          },
          "type": "boxShadow"
        }
      }
    },
    "font": {
      "parameter": {
        "scale": {
          "large": {
            "value": "1.3",
            "type": "other"
          },
          "small": {
            "value": "1.2",
            "type": "other"
          }
        }
      },
      "fontFamily": {
        "base": {
          "value": "Lato",
          "type": "fontFamilies"
        },
        "heading": {
          "value": "Lato",
          "type": "fontFamilies"
        }
      },
      "lineHeight": {
        "base": {
          "value": "160%",
          "type": "lineHeights"
        },
        "tighter": {
          "value": "145%",
          "type": "lineHeights"
        },
        "tightest": {
          "value": "125%",
          "type": "lineHeights"
        }
      },
      "fontWeight": {
        "regular": {
          "value": "Regular",
          "type": "fontWeights"
        },
        "bold": {
          "value": "Bold",
          "type": "fontWeights"
        },
        "regularNumber": {
          "value": "400",
          "type": "fontWeights"
        },
        "boldNumber": {
          "value": "600",
          "type": "fontWeights"
        },
        "regularItalic": {
          "value": "Italic",
          "type": "fontWeights"
        },
        "extrabold": {
          "value": "ExtraBold",
          "type": "fontWeights"
        },
        "extraboldNumber": {
          "value": "800",
          "type": "fontWeights"
        }
      },
      "letterSpacing": {
        "base": {
          "value": "0%",
          "type": "letterSpacing"
        },
        "looser": {
          "value": "15%",
          "type": "letterSpacing"
        }
      },
      "paragraphSpacing": {
        "none": {
          "value": "0",
          "type": "paragraphSpacing"
        },
        "base": {
          "value": "8",
          "type": "paragraphSpacing"
        }
      },
      "textCase": {
        "none": {
          "value": "none",
          "type": "textCase"
        },
        "uppercase": {
          "value": "uppercase",
          "type": "textCase"
        }
      },
      "textDecoration": {
        "none": {
          "value": "none",
          "type": "textDecoration"
        }
      },
      "size": {
        "small": {
          "xs": {
            "value": "{font.size.small.s} / {font.parameter.scale.small}",
            "type": "fontSizes"
          },
          "s": {
            "value": "{font.size.small.m} / {font.parameter.scale.small}",
            "type": "fontSizes"
          },
          "m": {
            "value": "14",
            "type": "fontSizes"
          },
          "l": {
            "value": "{font.size.small.m} * {font.parameter.scale.small}",
            "type": "fontSizes"
          },
          "xl": {
            "value": "{font.size.small.l} * {font.parameter.scale.small}",
            "type": "fontSizes"
          },
          "xxl": {
            "value": "{font.size.small.xl} * {font.parameter.scale.small}",
            "type": "fontSizes"
          },
          "xxxl": {
            "value": "{font.size.small.xxl} * {font.parameter.scale.small}",
            "type": "fontSizes"
          },
          "xxxxl": {
            "value": "{font.size.small.xxxl} * {font.parameter.scale.small}",
            "type": "fontSizes"
          }
        },
        "large": {
          "xs": {
            "value": "{font.size.large.s} / {font.parameter.scale.large}",
            "type": "fontSizes"
          },
          "s": {
            "value": "{font.size.large.m} / {font.parameter.scale.large}",
            "type": "fontSizes"
          },
          "m": {
            "value": "16",
            "type": "fontSizes"
          },
          "l": {
            "value": "{font.size.large.m} * {font.parameter.scale.large}",
            "type": "fontSizes"
          },
          "xl": {
            "value": "{font.size.large.l} * {font.parameter.scale.large}",
            "type": "fontSizes"
          },
          "xxl": {
            "value": "{font.size.large.xl} * {font.parameter.scale.large}",
            "type": "fontSizes"
          },
          "xxxl": {
            "value": "{font.size.large.xxl} * {font.parameter.scale.large}",
            "type": "fontSizes"
          },
          "xxxxl": {
            "value": "{font.size.large.xxxl} * {font.parameter.scale.large}",
            "type": "fontSizes"
          }
        }
      }
    },
    "size": {
      "min-content-width": {
        "value": "320",
        "type": "sizing"
      },
      "max-content-width": {
        "value": "1440",
        "type": "sizing"
      },
      "space": {
        "large": {
          "xxxs": {
            "value": "{font.size.large.m} * .25",
            "type": "spacing"
          },
          "xxs": {
            "value": "{font.size.large.m} * .5",
            "type": "spacing"
          },
          "xs": {
            "value": "{font.size.large.m} * .75",
            "type": "spacing"
          },
          "s": {
            "value": "{font.size.large.m} * 1",
            "type": "spacing"
          },
          "m": {
            "value": "{font.size.large.m} * 1.5",
            "type": "spacing"
          },
          "l": {
            "value": "{font.size.large.m} * 2",
            "type": "spacing"
          },
          "xl": {
            "value": "{font.size.large.m} * 3",
            "type": "spacing"
          },
          "xxl": {
            "value": "{font.size.large.m} * 4",
            "type": "spacing"
          },
          "xxxl": {
            "value": "{font.size.large.m} * 6",
            "type": "spacing"
          }
        },
        "small": {
          "xxxs": {
            "value": "{font.size.small.m} * .25",
            "type": "spacing"
          },
          "xxs": {
            "value": "{font.size.small.m} * .5",
            "type": "spacing"
          },
          "xs": {
            "value": "{font.size.small.m} * .75",
            "type": "spacing"
          },
          "s": {
            "value": "{font.size.small.m} * 1",
            "type": "spacing"
          },
          "m": {
            "value": "{font.size.small.m} * 1.5",
            "type": "spacing"
          },
          "l": {
            "value": "{font.size.small.m} * 2",
            "type": "spacing"
          },
          "xl": {
            "value": "{font.size.small.m} * 3",
            "type": "spacing"
          },
          "xxl": {
            "value": "{font.size.small.m} * 4",
            "type": "spacing"
          },
          "xxxl": {
            "value": "{font.size.small.m} * 6",
            "type": "spacing"
          }
        }
      },
      "spacer": {
        "large": {
          "xxxs": {
            "value": "{size.space.large.xxxs}",
            "type": "sizing"
          },
          "xxs": {
            "value": "{size.space.large.xxs}",
            "type": "sizing"
          },
          "xs": {
            "value": "{size.space.large.xs}",
            "type": "sizing"
          },
          "s": {
            "value": "{size.space.large.s}",
            "type": "sizing"
          },
          "m": {
            "value": "{size.space.large.m}",
            "type": "sizing"
          },
          "l": {
            "value": "{size.space.large.l}",
            "type": "sizing"
          },
          "xl": {
            "value": "{size.space.large.xl}",
            "type": "sizing"
          },
          "xxl": {
            "value": "{size.space.large.xxl}",
            "type": "sizing"
          },
          "xxxl": {
            "value": "{size.space.large.xxxl}",
            "type": "sizing"
          }
        }
      },
      "breakpoint": {
        "lg": {
          "value": "1200",
          "type": "sizing"
        },
        "xl": {
          "value": "1440",
          "type": "sizing"
        },
        "md": {
          "value": "960",
          "type": "sizing"
        },
        "sm": {
          "value": "640",
          "type": "sizing"
        },
        "xs": {
          "value": "480",
          "type": "sizing"
        }
      }
    },
    "radius": {
      "interactive": {
        "l": {
          "value": "5",
          "type": "borderRadius",
          "description": "Used for buttons or other interactive elements"
        },
        "s": {
          "value": "4",
          "type": "borderRadius"
        }
      },
      "information": {
        "l": {
          "value": "3",
          "type": "borderRadius",
          "description": "Used for info boxes"
        },
        "s": {
          "value": "2",
          "type": "borderRadius"
        }
      }
    },
    "stroke": {
      "default": {
        "value": "1",
        "type": "borderWidth"
      },
      "active": {
        "value": "2",
        "type": "borderWidth",
        "bold": {
          "value": "4",
          "type": "borderWidth"
        }
      },
      "active-bold": {
        "value": "4",
        "type": "borderWidth"
      }
    },
    "transition": {
      "duration": {
        "base": {
          "value": "300ms",
          "type": "other"
        },
        "quick": {
          "value": "100ms",
          "type": "other"
        }
      }
    }
  },
  "$themes": [],
  "$metadata": {
    "tokenSetOrder": [
      "global"
    ]
  }
}